mayako/Client.py
mayako/Command/CustomCommands.py
mayako/Command/StandardCommands.py
mayako/Command/__init__.py
mayako/Config.py
mayako/Devices/Actuator.py
mayako/Devices/CustomActuator.py
mayako/Devices/Device.py
mayako/Devices/LEDActuator.py
mayako/Devices/MicroController.py
mayako/Devices/Sensor.py
mayako/Devices/__init__.py
mayako/GUI/Controllers/AddDeviceController.py
mayako/GUI/Controllers/AddWiFiProfileController.py
mayako/GUI/Controllers/DeviceDetailsController.py
mayako/GUI/Controllers/DownloadArduinoController.py
mayako/GUI/Controllers/EditWiFiProfileController.py
mayako/GUI/Controllers/HomeController.py
mayako/GUI/Controllers/MainController.py
mayako/GUI/Controllers/__init__.py
mayako/GUI/Views/AddDeviceView.py
mayako/GUI/Views/AddWiFiProfileView.py
mayako/GUI/Views/DeviceDetailsView.py
mayako/GUI/Views/DownloadArduinoView.py
mayako/GUI/Views/EditWiFiProfileView.py
mayako/GUI/Views/HomeView.py
mayako/GUI/Views/MainView.py
mayako/GUI/Views/Root.py
mayako/GUI/Views/__init__.py
mayako/GUI/__init__.py
mayako/MayakoData.py
mayako/Models/AHRS.py
mayako/Models/Accelerometer.py
mayako/Models/ActuatorCapabilities.py
mayako/Models/BLEInfo.py
mayako/Models/BaseDataModel.py
mayako/Models/Button.py
mayako/Models/Gyroscope.py
mayako/Models/Heartrate.py
mayako/Models/MicrocontrollerCapabilities.py
mayako/Models/SensorCapabilities.py
mayako/Models/SerialInfo.py
mayako/Models/Temperature.py
mayako/Models/User.py
mayako/Models/WiFiProfile.py
mayako/Models/__init__.py
mayako/Network/BLE.py
mayako/Network/IntegrityMiddleware.py
mayako/Network/NetworkInterface.py
mayako/Network/NetworkManager.py
mayako/Network/Packet.py
mayako/Network/Serial.py
mayako/Network/WiFiUDP.py
mayako/Network/__init__.py
mayako/Observable.py
mayako/Service/ArduinoUploader.py
mayako/Service/BLEScanner.py
mayako/Service/ClientIPAddress.py
mayako/Service/GithubRepositoryDownloader.py
mayako/Service/MacAdress.py
mayako/Service/SerialScanner.py
mayako/Service/__init__.py
mayako/Utils/Exceptions.py
mayako_core-0.1.7.dist-info/LICENSE
mayako_core-0.1.7.dist-info/METADATA
mayako_core-0.1.7.dist-info/WHEEL
mayako_core-0.1.7.dist-info/RECORD
